MANIFEST.in
README.rst
fatslim
setup.cfg
setup.py
extra/fatslim-completion.bash
fatslim.egg-info/PKG-INFO
fatslim.egg-info/SOURCES.txt
fatslim.egg-info/dependency_links.txt
fatslim.egg-info/requires.txt
fatslim.egg-info/top_level.txt
fatslimlib/__init__.py
fatslimlib/builtins.py
fatslimlib/command.py
fatslimlib/core_analysis.c
fatslimlib/core_analysis.pxd
fatslimlib/core_analysis.pyx
fatslimlib/core_base.c
fatslimlib/core_base.pxd
fatslimlib/core_base.pyx
fatslimlib/core_datareading.c
fatslimlib/core_datareading.pyx
fatslimlib/core_geometry.c
fatslimlib/core_geometry.pxd
fatslimlib/core_geometry.pyx
fatslimlib/core_ns.c
fatslimlib/core_ns.pxd
fatslimlib/core_ns.pyx
fatslimlib/datareading.py
fatslimlib/typedefs.pxd
fatslimlib/util.py
fatslimlib/test/__init__.py
fatslimlib/test/test_00_cosmogony.py
fatslimlib/test/test_01_datareading.py
fatslimlib/test/test_02_core.py
fatslimlib/test/test_03_apl.py
fatslimlib/test/test_04_thickness.py
fatslimlib/test/test_05_userinterface.py
fatslimlib/test/data/__init__.py
fatslimlib/test/data/bilayer.gro
fatslimlib/test/data/bilayer.ndx
fatslimlib/test/data/bilayer_allatom.gro
fatslimlib/test/data/bilayer_allatom.ndx
fatslimlib/test/data/bilayer_chol.gro
fatslimlib/test/data/bilayer_chol.ndx
fatslimlib/test/data/bilayer_chol_apl_group.xvg
fatslimlib/test/data/bilayer_chol_apl_nogroup.xvg
fatslimlib/test/data/bilayer_ganglio.gro
fatslimlib/test/data/bilayer_ganglio.ndx
fatslimlib/test/data/bilayer_multi.gro
fatslimlib/test/data/bilayer_multi.ndx
fatslimlib/test/data/bilayer_peptide.gro
fatslimlib/test/data/bilayer_peptide.ndx
fatslimlib/test/data/bilayer_peptide_hydrogen.ndx
fatslimlib/test/data/bilayer_prot.gro
fatslimlib/test/data/bilayer_prot.ndx
fatslimlib/test/data/bilayer_prot_area.xvg
fatslimlib/test/data/deformed.gro
fatslimlib/test/data/deformed.ndx
fatslimlib/test/data/dppc_vesicle.gro
fatslimlib/test/data/dppc_vesicle.ndx
fatslimlib/test/data/dppc_vesicle.trr
fatslimlib/test/data/dppc_vesicle.xtc
fatslimlib/test/data/dppc_vesicle_apl.xvg
fatslimlib/test/data/dppc_vesicle_area.xvg
fatslimlib/test/data/dppc_vesicle_thickness.xvg
fatslimlib/test/data/model_big.gro
